AUTHORS
ChangeLog
README.md
requirements.txt
setup.cfg
setup.py
scraping_tools/__init__.py
scraping_tools/config.py
scraping_tools/driver.py
scraping_tools/logger.py
scraping_tools/notify.py
scraping_tools/pool.py
scraping_tools/proxy.py
scraping_tools/utils.py
scraping_tools.egg-info/PKG-INFO
scraping_tools.egg-info/SOURCES.txt
scraping_tools.egg-info/dependency_links.txt
scraping_tools.egg-info/not-zip-safe
scraping_tools.egg-info/pbr.json
scraping_tools.egg-info/requires.txt
scraping_tools.egg-info/top_level.txt