Metadata-Version: 1.1
Name: scraping-tools
Version: 1.0.0
Summary: Make it easy to write web-scrapers
Home-page: UNKNOWN
Author: Shay Arbov
Author-email: botify1000@gmail.com
License: MIT
Platform: UNKNOWN
Classifier: Operating System :: POSIX :: Linux
Classifier: Programming Language :: Python
Classifier: Programming Language :: Python :: 3
Classifier: Programming Language :: Python :: 3.6
